tests/__init__.py
tests/conftest.py
tests/test_client_simul_openssl1_0_2_DHE.py
tests/test_client_simul_openssl1_0_2_DSA.py
tests/test_client_simul_openssl3_0_0.py
tests/test_client_simul_openssl3_0_0_Ed25519.py
tests/test_client_simul_openssl3_0_0_Ed448.py
tests/test_client_simul_ssl2.py
tests/test_mod_text_server_profile.py
tlsmate_client_simul/__init__.py
tlsmate_client_simul/_version.py
tlsmate_client_simul/tlsmate_client_simul.py
tlsmate_client_simul/data/getClients.json
tlsmate_client_simul-1.0.1.dist-info/LICENSE.rst
tlsmate_client_simul-1.0.1.dist-info/METADATA
tlsmate_client_simul-1.0.1.dist-info/WHEEL
tlsmate_client_simul-1.0.1.dist-info/top_level.txt
tlsmate_client_simul-1.0.1.dist-info/zip-safe
tlsmate_client_simul-1.0.1.dist-info/RECORD
