Metadata-Version: 2.1
Name: tlsmate-client-simul
Version: 1.0.1
Summary: Simulates multiple different client bahviors
Home-page: https://gitlab.com/guballa/tlsmate_client_simul
Author: Jens Guballa
Author-email: jens@guballa.de
License: MIT
Project-URL: Bug Tracker, https://gitlab.com/guballa/tlsmate_client_simul/issues
Project-URL: Changelog, https://gitlab.com/guballa/tlsmate_client_simul/-/blob/master/CHANGELOG.rst
Project-URL: Source, https://gitlab.com/guballa/tlsmate_client_simul
Keywords: tls client simulator scan scanner server
Platform: any
Classifier: Development Status :: 3 - Alpha
Classifier: Intended Audience :: Developers
Classifier: License :: OSI Approved :: MIT License
Classifier: Operating System :: OS Independent
Classifier: Programming Language :: Python
Classifier: Programming Language :: Python :: 3.6
Classifier: Programming Language :: Python :: 3.7
Classifier: Programming Language :: Python :: 3.8
Classifier: Topic :: Software Development :: Libraries :: Python Modules
Requires-Python: <4,>=3.6
License-File: LICENSE.rst
Requires-Dist: tlsmate
Requires-Dist: dataclasses ; python_version < "3.7"
Requires-Dist: importlib-metadata ; python_version < "3.8"
Provides-Extra: dev
Requires-Dist: wheel ; extra == 'dev'
Requires-Dist: pytest ; extra == 'dev'
Requires-Dist: pytest-cov ; extra == 'dev'
Requires-Dist: black (==19.10b0) ; extra == 'dev'
Requires-Dist: flake8 ; extra == 'dev'
Requires-Dist: sphinx ; extra == 'dev'
Requires-Dist: sphinx-argparse ; extra == 'dev'
Requires-Dist: tox ; extra == 'dev'
Requires-Dist: sphinx-rtd-theme ; extra == 'dev'
